lib50/__init__.py
lib50/_api.py
lib50/_errors.py
lib50/authentication.py
lib50/config.py
lib50/crypto.py
lib50/locale/es/LC_MESSAGES/lib50.mo
lib50/locale/es/LC_MESSAGES/lib50.po
lib50/locale/vi/LC_MESSAGES/lib50.mo
lib50/locale/vi/LC_MESSAGES/lib50.po
lib50-3.2.1.dist-info/licenses/LICENSE
lib50-3.2.1.dist-info/METADATA
lib50-3.2.1.dist-info/WHEEL
lib50-3.2.1.dist-info/top_level.txt
lib50-3.2.1.dist-info/RECORD
